gcpinventory/__init__.py
gcpinventory/gcpinventory.py
gcpinventory-0.0.15.dist-info/METADATA
gcpinventory-0.0.15.dist-info/WHEEL
gcpinventory-0.0.15.dist-info/top_level.txt
gcpinventory-0.0.15.dist-info/RECORD
