Metadata-Version: 2.1
Name: gcpinventory
Version: 0.0.15
Summary: Service to manage GCP inventory resource
Home-page: https://github.com/hm-distro/professional-services/tree/master/tools/py-gce-utils
Author: hm-distro
License: Apache 2
Platform: any
Classifier: Programming Language :: Python :: 2
Classifier: License :: OSI Approved :: Apache Software License
Classifier: Operating System :: OS Independent
Requires-Dist: fabric
Requires-Dist: jq
